{
    "traceEvents": [
        {
            "args": {
                "name": "Allocators"
            },
            "name": "process_name",
            "ph": "M",
            "pid": 0
        },
        {
            "args": {
                "name": "/device:GPU:0/stream:15 Compute"
            },
            "name": "process_name",
            "ph": "M",
            "pid": 1
        },
        {
            "args": {
                "name": "/device:GPU:0/stream:15 Tensors"
            },
            "name": "process_name",
            "ph": "M",
            "pid": 2
        },
        {
            "args": {
                "name": "/job:localhost/replica:0/task:0/device:GPU:0 Compute"
            },
            "name": "process_name",
            "ph": "M",
            "pid": 3
        },
        {
            "args": {
                "name": "/job:localhost/replica:0/task:0/device:GPU:0 Tensors"
            },
            "name": "process_name",
            "ph": "M",
            "pid": 4
        },
        {
            "args": {
                "name": "/job:localhost/replica:0/task:0/device:CPU:0 Compute"
            },
            "name": "process_name",
            "ph": "M",
            "pid": 5
        },
        {
            "args": {
                "name": "/job:localhost/replica:0/task:0/device:CPU:0 Tensors"
            },
            "name": "process_name",
            "ph": "M",
            "pid": 6
        },
        {
            "args": {
                "name": "/device:GPU:0/stream:all Compute"
            },
            "name": "process_name",
            "ph": "M",
            "pid": 7
        },
        {
            "args": {
                "name": "/device:GPU:0/stream:all Tensors"
            },
            "name": "process_name",
            "ph": "M",
            "pid": 8
        },
        {
            "args": {
                "name": "/device:GPU:0/stream:14 Compute"
            },
            "name": "process_name",
            "ph": "M",
            "pid": 9
        },
        {
            "args": {
                "name": "/device:GPU:0/stream:14 Tensors"
            },
            "name": "process_name",
            "ph": "M",
            "pid": 10
        },
        {
            "args": {
                "name": "/device:GPU:0/stream:13 Compute"
            },
            "name": "process_name",
            "ph": "M",
            "pid": 11
        },
        {
            "args": {
                "name": "/device:GPU:0/stream:13 Tensors"
            },
            "name": "process_name",
            "ph": "M",
            "pid": 12
        },
        {
            "args": {
                "name": "/device:GPU:0/memcpy Compute"
            },
            "name": "process_name",
            "ph": "M",
            "pid": 13
        },
        {
            "args": {
                "name": "/device:GPU:0/memcpy Tensors"
            },
            "name": "process_name",
            "ph": "M",
            "pid": 14
        },
        {
            "args": {
                "name": "edge_16_Select",
                "op": "MEMCPYDtoH"
            },
            "tid": 0,
            "dur": 61,
            "ts": 1526057805727917,
            "name": "MEMCPYDtoH",
            "cat": "Op",
            "ph": "X",
            "pid": 1
        },
        {
            "args": {
                "name": "_SOURCE",
                "op": "NoOp"
            },
            "tid": 0,
            "dur": 14,
            "ts": 1526057805630133,
            "name": "NoOp",
            "cat": "Op",
            "ph": "X",
            "pid": 3
        },
        {
            "args": {
                "name": "Equal/y",
                "op": "Const"
            },
            "tid": 0,
            "dur": 31,
            "ts": 1526057805630158,
            "name": "Const",
            "cat": "Op",
            "ph": "X",
            "pid": 3
        },
        {
            "args": {
                "name": "ones_like",
                "op": "Const"
            },
            "tid": 0,
            "dur": 11,
            "ts": 1526057805630195,
            "name": "Const",
            "cat": "Op",
            "ph": "X",
            "pid": 3
        },
        {
            "args": {
                "name": "Assign/_125",
                "op": "Identity",
                "input0": "Assign/_124"
            },
            "tid": 0,
            "dur": 26,
            "ts": 1526057805664770,
            "name": "Identity",
            "cat": "Op",
            "ph": "X",
            "pid": 3
        },
        {
            "id": 0,
            "tid": 0,
            "ts": 1526057805650618,
            "name": "Assign",
            "cat": "DataFlow",
            "ph": "s",
            "pid": 5
        },
        {
            "id": 0,
            "tid": 0,
            "ts": 1526057805664770,
            "name": "Assign",
            "cat": "DataFlow",
            "ph": "t",
            "pid": 3
        },
        {
            "args": {
                "input1": "layer1/b/read/_107",
                "name": "add",
                "op": "Add",
                "input0": "MatMul/_105"
            },
            "tid": 0,
            "dur": 3472,
            "ts": 1526057805722855,
            "name": "Add",
            "cat": "Op",
            "ph": "X",
            "pid": 3
        },
        {
            "id": 1,
            "tid": 1,
            "ts": 1526057805722769,
            "name": "MatMul",
            "cat": "DataFlow",
            "ph": "s",
            "pid": 5
        },
        {
            "id": 1,
            "tid": 0,
            "ts": 1526057805722855,
            "name": "MatMul",
            "cat": "DataFlow",
            "ph": "t",
            "pid": 3
        },
        {
            "id": 2,
            "tid": 0,
            "ts": 1526057805630280,
            "name": "layer1/b/read",
            "cat": "DataFlow",
            "ph": "s",
            "pid": 5
        },
        {
            "id": 2,
            "tid": 0,
            "ts": 1526057805722855,
            "name": "layer1/b/read",
            "cat": "DataFlow",
            "ph": "t",
            "pid": 3
        },
        {
            "args": {
                "name": "Assign_1/_129",
                "op": "Identity",
                "input0": "Assign_1/_128"
            },
            "tid": 0,
            "dur": 22,
            "ts": 1526057805726810,
            "name": "Identity",
            "cat": "Op",
            "ph": "X",
            "pid": 3
        },
        {
            "id": 3,
            "tid": 0,
            "ts": 1526057805726649,
            "name": "Assign_1",
            "cat": "DataFlow",
            "ph": "s",
            "pid": 5
        },
        {
            "id": 3,
            "tid": 0,
            "ts": 1526057805726810,
            "name": "Assign_1",
            "cat": "DataFlow",
            "ph": "t",
            "pid": 3
        },
        {
            "args": {
                "name": "Sign",
                "op": "Sign",
                "input0": "add"
            },
            "tid": 1,
            "dur": 719,
            "ts": 1526057805726383,
            "name": "Sign",
            "cat": "Op",
            "ph": "X",
            "pid": 3
        },
        {
            "id": 4,
            "tid": 0,
            "ts": 1526057805726327,
            "name": "add",
            "cat": "DataFlow",
            "ph": "s",
            "pid": 3
        },
        {
            "id": 4,
            "tid": 1,
            "ts": 1526057805726383,
            "name": "add",
            "cat": "DataFlow",
            "ph": "t",
            "pid": 3
        },
        {
            "args": {
                "input1": "Equal/y",
                "name": "Equal",
                "op": "Equal",
                "input0": "Sign"
            },
            "tid": 0,
            "dur": 352,
            "ts": 1526057805727132,
            "name": "Equal",
            "cat": "Op",
            "ph": "X",
            "pid": 3
        },
        {
            "id": 5,
            "tid": 1,
            "ts": 1526057805727102,
            "name": "Sign",
            "cat": "DataFlow",
            "ph": "s",
            "pid": 3
        },
        {
            "id": 5,
            "tid": 0,
            "ts": 1526057805727132,
            "name": "Sign",
            "cat": "DataFlow",
            "ph": "t",
            "pid": 3
        },
        {
            "args": {
                "input1": "ones_like/_111",
                "name": "Select",
                "op": "Select",
                "input0": "Equal/_109",
                "input2": "Sign/_113"
            },
            "tid": 0,
            "dur": 104,
            "ts": 1526057805727715,
            "name": "Select",
            "cat": "Op",
            "ph": "X",
            "pid": 3
        },
        {
            "id": 6,
            "tid": 1,
            "ts": 1526057805727102,
            "name": "Sign",
            "cat": "DataFlow",
            "ph": "s",
            "pid": 3
        },
        {
            "id": 6,
            "tid": 0,
            "ts": 1526057805727715,
            "name": "Sign",
            "cat": "DataFlow",
            "ph": "t",
            "pid": 3
        },
        {
            "args": {
                "input1": "layer1/dropout/read/_117",
                "name": "Mul",
                "op": "Mul",
                "input0": "Select/_115"
            },
            "tid": 0,
            "dur": 3277,
            "ts": 1526057805728236,
            "name": "Mul",
            "cat": "Op",
            "ph": "X",
            "pid": 3
        },
        {
            "id": 7,
            "tid": 0,
            "ts": 1526057805630222,
            "name": "layer1/dropout/read",
            "cat": "DataFlow",
            "ph": "s",
            "pid": 5
        },
        {
            "id": 7,
            "tid": 0,
            "ts": 1526057805728236,
            "name": "layer1/dropout/read",
            "cat": "DataFlow",
            "ph": "t",
            "pid": 3
        },
        {
            "args": {
                "name": "Assign_2/_133",
                "op": "Identity",
                "input0": "Assign_2/_132"
            },
            "tid": 0,
            "dur": 15,
            "ts": 1526057805731968,
            "name": "Identity",
            "cat": "Op",
            "ph": "X",
            "pid": 3
        },
        {
            "id": 8,
            "tid": 0,
            "ts": 1526057805731729,
            "name": "Assign_2",
            "cat": "DataFlow",
            "ph": "s",
            "pid": 5
        },
        {
            "id": 8,
            "tid": 0,
            "ts": 1526057805731968,
            "name": "Assign_2",
            "cat": "DataFlow",
            "ph": "t",
            "pid": 3
        },
        {
            "args": {
                "input1": "^Assign_1/_129",
                "name": "group_deps",
                "op": "NoOp",
                "input0": "^Assign/_125",
                "input2": "^Assign_2/_133"
            },
            "tid": 0,
            "dur": 7,
            "ts": 1526057805731988,
            "name": "NoOp",
            "cat": "Op",
            "ph": "X",
            "pid": 3
        },
        {
            "args": {
                "name": "_SOURCE",
                "op": "NoOp"
            },
            "tid": 0,
            "dur": 15,
            "ts": 1526057805630121,
            "name": "NoOp",
            "cat": "Op",
            "ph": "X",
            "pid": 5
        },
        {
            "args": {
                "name": "layer1/dropout",
                "op": "VariableV2"
            },
            "tid": 0,
            "dur": 51,
            "ts": 1526057805630154,
            "name": "VariableV2",
            "cat": "Op",
            "ph": "X",
            "pid": 5
        },
        {
            "args": {
                "name": "layer1/dropout/read",
                "op": "Identity",
                "input0": "layer1/dropout"
            },
            "tid": 0,
            "dur": 11,
            "ts": 1526057805630211,
            "name": "Identity",
            "cat": "Op",
            "ph": "X",
            "pid": 5
        },
        {
            "args": {
                "name": "layer1/b",
                "op": "VariableV2"
            },
            "tid": 0,
            "dur": 18,
            "ts": 1526057805630249,
            "name": "VariableV2",
            "cat": "Op",
            "ph": "X",
            "pid": 5
        },
        {
            "args": {
                "name": "layer1/b/read",
                "op": "Identity",
                "input0": "layer1/b"
            },
            "tid": 0,
            "dur": 9,
            "ts": 1526057805630271,
            "name": "Identity",
            "cat": "Op",
            "ph": "X",
            "pid": 5
        },
        {
            "args": {
                "name": "layer1/W",
                "op": "VariableV2"
            },
            "tid": 0,
            "dur": 14,
            "ts": 1526057805630302,
            "name": "VariableV2",
            "cat": "Op",
            "ph": "X",
            "pid": 5
        },
        {
            "args": {
                "name": "layer1/W/read",
                "op": "Identity",
                "input0": "layer1/W"
            },
            "tid": 0,
            "dur": 8,
            "ts": 1526057805630320,
            "name": "Identity",
            "cat": "Op",
            "ph": "X",
            "pid": 5
        },
        {
            "args": {
                "name": "global/X_tr",
                "op": "VariableV2"
            },
            "tid": 0,
            "dur": 13,
            "ts": 1526057805630332,
            "name": "VariableV2",
            "cat": "Op",
            "ph": "X",
            "pid": 5
        },
        {
            "args": {
                "name": "global/X_tr/read",
                "op": "Identity",
                "input0": "global/X_tr"
            },
            "tid": 0,
            "dur": 8,
            "ts": 1526057805630349,
            "name": "Identity",
            "cat": "Op",
            "ph": "X",
            "pid": 5
        },
        {
            "args": {
                "name": "layer1/input",
                "op": "VariableV2"
            },
            "tid": 0,
            "dur": 45,
            "ts": 1526057805644780,
            "name": "VariableV2",
            "cat": "Op",
            "ph": "X",
            "pid": 5
        },
        {
            "args": {
                "input1": "global/X_tr/read",
                "name": "Assign",
                "op": "Assign",
                "input0": "layer1/input"
            },
            "tid": 0,
            "dur": 5783,
            "ts": 1526057805644835,
            "name": "Assign",
            "cat": "Op",
            "ph": "X",
            "pid": 5
        },
        {
            "args": {
                "name": "Assign/_122",
                "op": "Const",
                "input0": "^Assign"
            },
            "tid": 0,
            "dur": 19,
            "ts": 1526057805650640,
            "name": "Const",
            "cat": "Op",
            "ph": "X",
            "pid": 5
        },
        {
            "args": {
                "name": "layer1/activation",
                "op": "VariableV2"
            },
            "tid": 0,
            "dur": 27,
            "ts": 1526057805664820,
            "name": "VariableV2",
            "cat": "Op",
            "ph": "X",
            "pid": 5
        },
        {
            "args": {
                "name": "layer1/output",
                "op": "VariableV2"
            },
            "tid": 0,
            "dur": 15,
            "ts": 1526057805664864,
            "name": "VariableV2",
            "cat": "Op",
            "ph": "X",
            "pid": 5
        },
        {
            "args": {
                "input1": "layer1/W/read",
                "name": "MatMul",
                "op": "MatMul",
                "input0": "global/X_tr/read"
            },
            "tid": 1,
            "dur": 92407,
            "ts": 1526057805630362,
            "name": "MatMul",
            "cat": "Op",
            "ph": "X",
            "pid": 5
        },
        {
            "id": 9,
            "tid": 0,
            "ts": 1526057805630357,
            "name": "global/X_tr/read",
            "cat": "DataFlow",
            "ph": "s",
            "pid": 5
        },
        {
            "id": 9,
            "tid": 1,
            "ts": 1526057805630362,
            "name": "global/X_tr/read",
            "cat": "DataFlow",
            "ph": "t",
            "pid": 5
        },
        {
            "id": 10,
            "tid": 0,
            "ts": 1526057805630328,
            "name": "layer1/W/read",
            "cat": "DataFlow",
            "ph": "s",
            "pid": 5
        },
        {
            "id": 10,
            "tid": 1,
            "ts": 1526057805630362,
            "name": "layer1/W/read",
            "cat": "DataFlow",
            "ph": "t",
            "pid": 5
        },
        {
            "args": {
                "input1": "add/_121",
                "name": "Assign_1",
                "op": "Assign",
                "input0": "layer1/activation"
            },
            "tid": 0,
            "dur": 184,
            "ts": 1526057805726465,
            "name": "Assign",
            "cat": "Op",
            "ph": "X",
            "pid": 5
        },
        {
            "id": 11,
            "tid": 0,
            "ts": 1526057805726327,
            "name": "add",
            "cat": "DataFlow",
            "ph": "s",
            "pid": 3
        },
        {
            "id": 11,
            "tid": 0,
            "ts": 1526057805726465,
            "name": "add",
            "cat": "DataFlow",
            "ph": "t",
            "pid": 5
        },
        {
            "args": {
                "name": "Assign_1/_126",
                "op": "Const",
                "input0": "^Assign_1"
            },
            "tid": 0,
            "dur": 14,
            "ts": 1526057805726655,
            "name": "Const",
            "cat": "Op",
            "ph": "X",
            "pid": 5
        },
        {
            "args": {
                "input1": "Mul/_119",
                "name": "Assign_2",
                "op": "Assign",
                "input0": "layer1/output"
            },
            "tid": 0,
            "dur": 164,
            "ts": 1526057805731565,
            "name": "Assign",
            "cat": "Op",
            "ph": "X",
            "pid": 5
        },
        {
            "id": 12,
            "tid": 0,
            "ts": 1526057805731513,
            "name": "Mul",
            "cat": "DataFlow",
            "ph": "s",
            "pid": 3
        },
        {
            "id": 12,
            "tid": 0,
            "ts": 1526057805731565,
            "name": "Mul",
            "cat": "DataFlow",
            "ph": "t",
            "pid": 5
        },
        {
            "args": {
                "name": "Assign_2/_130",
                "op": "Const",
                "input0": "^Assign_2"
            },
            "tid": 0,
            "dur": 12,
            "ts": 1526057805731736,
            "name": "Const",
            "cat": "Op",
            "ph": "X",
            "pid": 5
        },
        {
            "args": {
                "name": "Select",
                "op": "Select"
            },
            "tid": 0,
            "dur": 10,
            "ts": 1526057805727799,
            "name": "Select",
            "cat": "Op",
            "ph": "X",
            "pid": 7
        },
        {
            "args": {
                "name": "edge_14_ones_like",
                "op": "MEMCPYHtoD"
            },
            "tid": 0,
            "dur": 4,
            "ts": 19972801841097316,
            "name": "MEMCPYHtoD",
            "cat": "Op",
            "ph": "X",
            "pid": 9
        },
        {
            "args": {
                "name": "edge_15_Sign",
                "op": "MEMCPYHtoD"
            },
            "tid": 1,
            "dur": 65,
            "ts": 1526057805727224,
            "name": "MEMCPYHtoD",
            "cat": "Op",
            "ph": "X",
            "pid": 9
        },
        {
            "args": {
                "name": "edge_13_Equal",
                "op": "MEMCPYHtoD"
            },
            "tid": 1,
            "dur": 17,
            "ts": 1526057805727572,
            "name": "MEMCPYHtoD",
            "cat": "Op",
            "ph": "X",
            "pid": 9
        },
        {
            "args": {
                "name": "Select",
                "op": "Select"
            },
            "tid": 0,
            "dur": 10,
            "ts": 1526057805727799,
            "name": "Select",
            "cat": "Op",
            "ph": "X",
            "pid": 11
        },
        {
            "args": {
                "name": "edge_14_ones_like",
                "op": "MEMCPYHtoD"
            },
            "tid": 0,
            "dur": 4,
            "ts": 19972801841097316,
            "name": "MEMCPYHtoD",
            "cat": "Op",
            "ph": "X",
            "pid": 13
        },
        {
            "args": {
                "name": "edge_15_Sign",
                "op": "MEMCPYHtoD"
            },
            "tid": 1,
            "dur": 65,
            "ts": 1526057805727224,
            "name": "MEMCPYHtoD",
            "cat": "Op",
            "ph": "X",
            "pid": 13
        },
        {
            "args": {
                "name": "edge_13_Equal",
                "op": "MEMCPYHtoD"
            },
            "tid": 1,
            "dur": 17,
            "ts": 1526057805727572,
            "name": "MEMCPYHtoD",
            "cat": "Op",
            "ph": "X",
            "pid": 13
        },
        {
            "args": {
                "name": "edge_16_Select",
                "op": "MEMCPYDtoH"
            },
            "tid": 1,
            "dur": 61,
            "ts": 1526057805727917,
            "name": "MEMCPYDtoH",
            "cat": "Op",
            "ph": "X",
            "pid": 13
        }
    ]
}